{
    "meta": {
        "currency": "USD",
        "symbol": "AAPL",
        "exchangeName": "NMS",
        "instrumentType": "EQUITY",
        "firstTradeDate": 345479400,
        "regularMarketTime": 1616184003,
        "gmtoffset": -14400,
        "timezone": "EDT",
        "exchangeTimezoneName": "America/New_York",
        "regularMarketPrice": 119.99,
        "chartPreviousClose": 129.87,
        "previousClose": 120.53,
        "scale": 3,
        "priceHint": 2,
        "dataGranularity": "1h",
        "range": ""
    },
    "items": {
        "1614004200": {
            "date": "22-02-2021",
            "open": 128.01,
            "high": 129.72,
            "low": 126.82,
            "close": 127.13
        },
        "1614007800": {
            "date": "22-02-2021",
            "open": 127.11,
            "high": 127.25,
            "low": 125.6,
            "close": 126.86
        },
        "1614011400": {
            "date": "22-02-2021",
            "open": 126.86,
            "high": 127.25,
            "low": 126.5,
            "close": 126.72
        },
        "1614015000": {
            "date": "22-02-2021",
            "open": 126.71,
            "high": 127.32,
            "low": 126.64,
            "close": 127.26
        },
        "1614018600": {
            "date": "22-02-2021",
            "open": 127.25,
            "high": 127.96,
            "low": 127.24,
            "close": 127.67
        },
        "1614022200": {
            "date": "22-02-2021",
            "open": 127.66,
            "high": 127.71,
            "low": 126.46,
            "close": 126.49
        },
        "1614025800": {
            "date": "22-02-2021",
            "open": 126.48,
            "high": 126.75,
            "low": 126,
            "close": 126.01
        },
        "1614090600": {
            "date": "23-02-2021",
            "open": 123.76,
            "high": 123.79,
            "low": 118.5,
            "close": 123.21
        },
        "1614094200": {
            "date": "23-02-2021",
            "open": 123.2,
            "high": 124.12,
            "low": 122.57,
            "close": 123.03
        },
        "1614097800": {
            "date": "23-02-2021",
            "open": 123.01,
            "high": 123.25,
            "low": 121.31,
            "close": 122.42
        },
        "1614101400": {
            "date": "23-02-2021",
            "open": 122.42,
            "high": 123.75,
            "low": 121.5,
            "close": 123.54
        },
        "1614105000": {
            "date": "23-02-2021",
            "open": 123.56,
            "high": 125.19,
            "low": 123.46,
            "close": 124.75
        },
        "1614108600": {
            "date": "23-02-2021",
            "open": 124.77,
            "high": 126.7,
            "low": 124.4,
            "close": 126.65
        },
        "1614112200": {
            "date": "23-02-2021",
            "open": 126.64,
            "high": 126.71,
            "low": 125.66,
            "close": 125.85
        },
        "1614177000": {
            "date": "24-02-2021",
            "open": 125.31,
            "high": 125.35,
            "low": 122.23,
            "close": 124.01
        },
        "1614180600": {
            "date": "24-02-2021",
            "open": 124.02,
            "high": 124.93,
            "low": 123.5,
            "close": 124.56
        },
        "1614184200": {
            "date": "24-02-2021",
            "open": 124.56,
            "high": 125.11,
            "low": 124.15,
            "close": 125.11
        },
        "1614187800": {
            "date": "24-02-2021",
            "open": 125.11,
            "high": 125.14,
            "low": 123.95,
            "close": 124.45
        },
        "1614191400": {
            "date": "24-02-2021",
            "open": 124.46,
            "high": 125.18,
            "low": 124.32,
            "close": 124.46
        },
        "1614195000": {
            "date": "24-02-2021",
            "open": 124.46,
            "high": 124.93,
            "low": 124.21,
            "close": 124.93
        },
        "1614198600": {
            "date": "24-02-2021",
            "open": 124.92,
            "high": 125.56,
            "low": 124.72,
            "close": 125.31
        },
        "1614263400": {
            "date": "25-02-2021",
            "open": 124.75,
            "high": 126.46,
            "low": 123.61,
            "close": 124.02
        },
        "1614267000": {
            "date": "25-02-2021",
            "open": 124.03,
            "high": 124.23,
            "low": 123.13,
            "close": 123.69
        },
        "1614270600": {
            "date": "25-02-2021",
            "open": 123.69,
            "high": 123.71,
            "low": 122.12,
            "close": 122.25
        },
        "1614274200": {
            "date": "25-02-2021",
            "open": 122.25,
            "high": 122.63,
            "low": 120.75,
            "close": 122.12
        },
        "1614277800": {
            "date": "25-02-2021",
            "open": 122.12,
            "high": 123.43,
            "low": 121.76,
            "close": 123.15
        },
        "1614281400": {
            "date": "25-02-2021",
            "open": 123.15,
            "high": 123.23,
            "low": 121.24,
            "close": 121.32
        },
        "1614285000": {
            "date": "25-02-2021",
            "open": 121.32,
            "high": 122.06,
            "low": 120.54,
            "close": 120.99
        },
        "1614349800": {
            "date": "26-02-2021",
            "open": 122.59,
            "high": 123.93,
            "low": 121.29,
            "close": 121.5
        },
        "1614353400": {
            "date": "26-02-2021",
            "open": 121.47,
            "high": 124.21,
            "low": 121.4,
            "close": 123.5
        },
        "1614357000": {
            "date": "26-02-2021",
            "open": 123.51,
            "high": 124.76,
            "low": 123.42,
            "close": 124.2
        },
        "1614360600": {
            "date": "26-02-2021",
            "open": 124.2,
            "high": 124.41,
            "low": 123.25,
            "close": 124.28
        },
        "1614364200": {
            "date": "26-02-2021",
            "open": 124.29,
            "high": 124.35,
            "low": 122.76,
            "close": 123.05
        },
        "1614367800": {
            "date": "26-02-2021",
            "open": 123.04,
            "high": 124.36,
            "low": 122.9,
            "close": 123.64
        },
        "1614371400": {
            "date": "26-02-2021",
            "open": 123.63,
            "high": 124.85,
            "low": 121.21,
            "close": 121.21
        },
        "1614609000": {
            "date": "01-03-2021",
            "open": 123.5,
            "high": 125.25,
            "low": 122.79,
            "close": 125.08
        },
        "1614612600": {
            "date": "01-03-2021",
            "open": 125.08,
            "high": 126.15,
            "low": 124.88,
            "close": 125.88
        },
        "1614616200": {
            "date": "01-03-2021",
            "open": 125.88,
            "high": 126.62,
            "low": 125.79,
            "close": 126.23
        },
        "1614619800": {
            "date": "01-03-2021",
            "open": 126.24,
            "high": 126.4,
            "low": 125.67,
            "close": 126.21
        },
        "1614623400": {
            "date": "01-03-2021",
            "open": 126.21,
            "high": 127.23,
            "low": 126.09,
            "close": 127.11
        },
        "1614627000": {
            "date": "01-03-2021",
            "open": 127.11,
            "high": 127.75,
            "low": 126.91,
            "close": 127.56
        },
        "1614630600": {
            "date": "01-03-2021",
            "open": 127.57,
            "high": 127.93,
            "low": 127.27,
            "close": 127.79
        },
        "1614695400": {
            "date": "02-03-2021",
            "open": 128.41,
            "high": 128.72,
            "low": 125.98,
            "close": 126.07
        },
        "1614699000": {
            "date": "02-03-2021",
            "open": 126.06,
            "high": 126.45,
            "low": 125.5,
            "close": 125.96
        },
        "1614702600": {
            "date": "02-03-2021",
            "open": 125.96,
            "high": 126.25,
            "low": 125.46,
            "close": 126.09
        },
        "1614706200": {
            "date": "02-03-2021",
            "open": 126.09,
            "high": 126.68,
            "low": 126,
            "close": 126.13
        },
        "1614709800": {
            "date": "02-03-2021",
            "open": 126.13,
            "high": 126.38,
            "low": 125.58,
            "close": 125.65
        },
        "1614713400": {
            "date": "02-03-2021",
            "open": 125.65,
            "high": 126.31,
            "low": 125.48,
            "close": 125.59
        },
        "1614717000": {
            "date": "02-03-2021",
            "open": 125.6,
            "high": 125.99,
            "low": 125.01,
            "close": 125.16
        },
        "1614781800": {
            "date": "03-03-2021",
            "open": 125.54,
            "high": 125.71,
            "low": 123.11,
            "close": 123.71
        },
        "1614785400": {
            "date": "03-03-2021",
            "open": 123.71,
            "high": 124.79,
            "low": 123.46,
            "close": 124.78
        },
        "1614789000": {
            "date": "03-03-2021",
            "open": 124.77,
            "high": 124.93,
            "low": 123.93,
            "close": 124.04
        },
        "1614792600": {
            "date": "03-03-2021",
            "open": 124.03,
            "high": 124.17,
            "low": 123.35,
            "close": 123.87
        },
        "1614796200": {
            "date": "03-03-2021",
            "open": 123.87,
            "high": 123.87,
            "low": 122.16,
            "close": 122.25
        },
        "1614799800": {
            "date": "03-03-2021",
            "open": 122.25,
            "high": 122.97,
            "low": 121.84,
            "close": 122.49
        },
        "1614803400": {
            "date": "03-03-2021",
            "open": 122.49,
            "high": 122.97,
            "low": 122,
            "close": 122.06
        },
        "1614868200": {
            "date": "04-03-2021",
            "open": 122.19,
            "high": 123.6,
            "low": 120.32,
            "close": 121.43
        },
        "1614871800": {
            "date": "04-03-2021",
            "open": 121.43,
            "high": 123.28,
            "low": 121.09,
            "close": 122.19
        },
        "1614875400": {
            "date": "04-03-2021",
            "open": 122.19,
            "high": 123.19,
            "low": 120.68,
            "close": 121.28
        },
        "1614879000": {
            "date": "04-03-2021",
            "open": 121.27,
            "high": 121.48,
            "low": 119.63,
            "close": 120.54
        },
        "1614882600": {
            "date": "04-03-2021",
            "open": 120.54,
            "high": 120.56,
            "low": 118.62,
            "close": 120.18
        },
        "1614886200": {
            "date": "04-03-2021",
            "open": 120.18,
            "high": 120.86,
            "low": 119.51,
            "close": 119.95
        },
        "1614889800": {
            "date": "04-03-2021",
            "open": 119.94,
            "high": 120.39,
            "low": 119.56,
            "close": 120.22
        },
        "1614954600": {
            "date": "05-03-2021",
            "open": 120.98,
            "high": 121.67,
            "low": 118.54,
            "close": 118.77
        },
        "1614958200": {
            "date": "05-03-2021",
            "open": 118.78,
            "high": 119.82,
            "low": 117.57,
            "close": 117.72
        },
        "1614961800": {
            "date": "05-03-2021",
            "open": 117.74,
            "high": 119.58,
            "low": 117.74,
            "close": 119.43
        },
        "1614965400": {
            "date": "05-03-2021",
            "open": 119.43,
            "high": 119.99,
            "low": 118.46,
            "close": 119.94
        },
        "1614969000": {
            "date": "05-03-2021",
            "open": 119.94,
            "high": 120.7,
            "low": 119.64,
            "close": 120.47
        },
        "1614972600": {
            "date": "05-03-2021",
            "open": 120.48,
            "high": 121.56,
            "low": 120.47,
            "close": 121.23
        },
        "1614976200": {
            "date": "05-03-2021",
            "open": 121.23,
            "high": 121.93,
            "low": 121.02,
            "close": 121.39
        },
        "1615213800": {
            "date": "08-03-2021",
            "open": 120.5,
            "high": 120.62,
            "low": 118.06,
            "close": 119
        },
        "1615217400": {
            "date": "08-03-2021",
            "open": 119.02,
            "high": 119.48,
            "low": 118.17,
            "close": 118.5
        },
        "1615221000": {
            "date": "08-03-2021",
            "open": 118.5,
            "high": 118.53,
            "low": 117.4,
            "close": 118.22
        },
        "1615224600": {
            "date": "08-03-2021",
            "open": 118.21,
            "high": 118.26,
            "low": 117.66,
            "close": 118.18
        },
        "1615228200": {
            "date": "08-03-2021",
            "open": 118.18,
            "high": 118.22,
            "low": 116.76,
            "close": 117.52
        },
        "1615231800": {
            "date": "08-03-2021",
            "open": 117.51,
            "high": 117.82,
            "low": 116.65,
            "close": 116.82
        },
        "1615235400": {
            "date": "08-03-2021",
            "open": 116.82,
            "high": 117.39,
            "low": 116.21,
            "close": 116.4
        },
        "1615300200": {
            "date": "09-03-2021",
            "open": 119.25,
            "high": 121.56,
            "low": 118.8,
            "close": 121.32
        },
        "1615303800": {
            "date": "09-03-2021",
            "open": 121.32,
            "high": 121.37,
            "low": 120.05,
            "close": 120.43
        },
        "1615307400": {
            "date": "09-03-2021",
            "open": 120.43,
            "high": 121.24,
            "low": 120.2,
            "close": 121.1
        },
        "1615311000": {
            "date": "09-03-2021",
            "open": 121.1,
            "high": 121.69,
            "low": 120.75,
            "close": 121.57
        },
        "1615314600": {
            "date": "09-03-2021",
            "open": 121.57,
            "high": 121.95,
            "low": 121.1,
            "close": 121.15
        },
        "1615318200": {
            "date": "09-03-2021",
            "open": 121.16,
            "high": 122.06,
            "low": 121.07,
            "close": 121.72
        },
        "1615321800": {
            "date": "09-03-2021",
            "open": 121.73,
            "high": 121.95,
            "low": 120.82,
            "close": 121.08
        },
        "1615386600": {
            "date": "10-03-2021",
            "open": 121.69,
            "high": 122.17,
            "low": 119.79,
            "close": 119.93
        },
        "1615390200": {
            "date": "10-03-2021",
            "open": 119.92,
            "high": 120.49,
            "low": 119.45,
            "close": 120.43
        },
        "1615393800": {
            "date": "10-03-2021",
            "open": 120.42,
            "high": 120.5,
            "low": 119.79,
            "close": 119.86
        },
        "1615397400": {
            "date": "10-03-2021",
            "open": 119.87,
            "high": 120.41,
            "low": 119.55,
            "close": 120.33
        },
        "1615401000": {
            "date": "10-03-2021",
            "open": 120.32,
            "high": 120.48,
            "low": 119.74,
            "close": 120.31
        },
        "1615404600": {
            "date": "10-03-2021",
            "open": 120.31,
            "high": 120.92,
            "low": 120.21,
            "close": 120.36
        },
        "1615408200": {
            "date": "10-03-2021",
            "open": 120.36,
            "high": 120.56,
            "low": 119.86,
            "close": 119.97
        },
        "1615473000": {
            "date": "11-03-2021",
            "open": 122.17,
            "high": 123.05,
            "low": 121.26,
            "close": 121.4
        },
        "1615476600": {
            "date": "11-03-2021",
            "open": 121.39,
            "high": 122.68,
            "low": 121.39,
            "close": 122.66
        },
        "1615480200": {
            "date": "11-03-2021",
            "open": 122.66,
            "high": 122.77,
            "low": 121.86,
            "close": 122.01
        },
        "1615483800": {
            "date": "11-03-2021",
            "open": 122,
            "high": 122.31,
            "low": 121.66,
            "close": 121.77
        },
        "1615487400": {
            "date": "11-03-2021",
            "open": 121.77,
            "high": 122.05,
            "low": 121.56,
            "close": 121.82
        },
        "1615491000": {
            "date": "11-03-2021",
            "open": 121.82,
            "high": 122.23,
            "low": 121.7,
            "close": 122.17
        },
        "1615494600": {
            "date": "11-03-2021",
            "open": 122.17,
            "high": 122.21,
            "low": 121.76,
            "close": 121.96
        },
        "1615559400": {
            "date": "12-03-2021",
            "open": 120.35,
            "high": 120.47,
            "low": 119.25,
            "close": 119.42
        },
        "1615563000": {
            "date": "12-03-2021",
            "open": 119.44,
            "high": 119.94,
            "low": 119.39,
            "close": 119.82
        },
        "1615566600": {
            "date": "12-03-2021",
            "open": 119.82,
            "high": 120.88,
            "low": 119.59,
            "close": 120.84
        },
        "1615570200": {
            "date": "12-03-2021",
            "open": 120.85,
            "high": 121.07,
            "low": 120.43,
            "close": 120.9
        },
        "1615573800": {
            "date": "12-03-2021",
            "open": 120.89,
            "high": 121.01,
            "low": 120.5,
            "close": 120.59
        },
        "1615577400": {
            "date": "12-03-2021",
            "open": 120.6,
            "high": 120.9,
            "low": 120.46,
            "close": 120.75
        },
        "1615581000": {
            "date": "12-03-2021",
            "open": 120.76,
            "high": 121.17,
            "low": 120.68,
            "close": 121.04
        },
        "1615815000": {
            "date": "15-03-2021",
            "open": 121.26,
            "high": 123.57,
            "low": 120.42,
            "close": 122.6
        },
        "1615818600": {
            "date": "15-03-2021",
            "open": 122.6,
            "high": 123.23,
            "low": 122.24,
            "close": 122.39
        },
        "1615822200": {
            "date": "15-03-2021",
            "open": 122.39,
            "high": 122.49,
            "low": 122.04,
            "close": 122.33
        },
        "1615825800": {
            "date": "15-03-2021",
            "open": 122.34,
            "high": 122.72,
            "low": 122.24,
            "close": 122.68
        },
        "1615829400": {
            "date": "15-03-2021",
            "open": 122.68,
            "high": 123.64,
            "low": 122.65,
            "close": 123.48
        },
        "1615833000": {
            "date": "15-03-2021",
            "open": 123.48,
            "high": 123.58,
            "low": 123.06,
            "close": 123.35
        },
        "1615836600": {
            "date": "15-03-2021",
            "open": 123.35,
            "high": 124,
            "low": 123.28,
            "close": 124
        },
        "1615901400": {
            "date": "16-03-2021",
            "open": 125.7,
            "high": 126.84,
            "low": 125.08,
            "close": 126.41
        },
        "1615905000": {
            "date": "16-03-2021",
            "open": 126.42,
            "high": 127.22,
            "low": 126.25,
            "close": 126.75
        },
        "1615908600": {
            "date": "16-03-2021",
            "open": 126.76,
            "high": 126.9,
            "low": 125.33,
            "close": 125.46
        },
        "1615912200": {
            "date": "16-03-2021",
            "open": 125.46,
            "high": 126.28,
            "low": 125.42,
            "close": 125.84
        },
        "1615915800": {
            "date": "16-03-2021",
            "open": 125.85,
            "high": 125.86,
            "low": 124.91,
            "close": 125.02
        },
        "1615919400": {
            "date": "16-03-2021",
            "open": 125.01,
            "high": 125.74,
            "low": 124.71,
            "close": 125.61
        },
        "1615923000": {
            "date": "16-03-2021",
            "open": 125.62,
            "high": 125.93,
            "low": 125.39,
            "close": 125.57
        },
        "1615987800": {
            "date": "17-03-2021",
            "open": 124.05,
            "high": 124.21,
            "low": 122.79,
            "close": 123.46
        },
        "1615991400": {
            "date": "17-03-2021",
            "open": 123.45,
            "high": 123.58,
            "low": 122.58,
            "close": 122.9
        },
        "1615995000": {
            "date": "17-03-2021",
            "open": 122.9,
            "high": 122.97,
            "low": 122.39,
            "close": 122.82
        },
        "1615998600": {
            "date": "17-03-2021",
            "open": 122.82,
            "high": 122.93,
            "low": 122.34,
            "close": 122.74
        },
        "1616002200": {
            "date": "17-03-2021",
            "open": 122.75,
            "high": 124.49,
            "low": 122.58,
            "close": 123.88
        },
        "1616005800": {
            "date": "17-03-2021",
            "open": 123.88,
            "high": 125.86,
            "low": 123.58,
            "close": 125.08
        },
        "1616009400": {
            "date": "17-03-2021",
            "open": 125.09,
            "high": 125.41,
            "low": 124.29,
            "close": 124.8
        },
        "1616074200": {
            "date": "18-03-2021",
            "open": 122.88,
            "high": 123.18,
            "low": 121.59,
            "close": 122.18
        },
        "1616077800": {
            "date": "18-03-2021",
            "open": 122.18,
            "high": 122.73,
            "low": 121.96,
            "close": 122.21
        },
        "1616081400": {
            "date": "18-03-2021",
            "open": 122.21,
            "high": 122.59,
            "low": 121.81,
            "close": 122.32
        },
        "1616085000": {
            "date": "18-03-2021",
            "open": 122.32,
            "high": 122.34,
            "low": 121.7,
            "close": 121.9
        },
        "1616088600": {
            "date": "18-03-2021",
            "open": 121.9,
            "high": 122.21,
            "low": 121.38,
            "close": 121.43
        },
        "1616092200": {
            "date": "18-03-2021",
            "open": 121.43,
            "high": 121.54,
            "low": 120.65,
            "close": 121.06
        },
        "1616095800": {
            "date": "18-03-2021",
            "open": 121.04,
            "high": 121.08,
            "low": 120.32,
            "close": 120.53
        },
        "1616160600": {
            "date": "19-03-2021",
            "open": 120.62,
            "high": 121.43,
            "low": 119.68,
            "close": 120.12
        },
        "1616164200": {
            "date": "19-03-2021",
            "open": 120.11,
            "high": 120.73,
            "low": 119.84,
            "close": 120.01
        },
        "1616167800": {
            "date": "19-03-2021",
            "open": 120.01,
            "high": 120.85,
            "low": 119.93,
            "close": 120.56
        },
        "1616171400": {
            "date": "19-03-2021",
            "open": 120.55,
            "high": 121.16,
            "low": 120.49,
            "close": 120.61
        },
        "1616175000": {
            "date": "19-03-2021",
            "open": 120.61,
            "high": 120.68,
            "low": 120,
            "close": 120.28
        },
        "1616178600": {
            "date": "19-03-2021",
            "open": 120.29,
            "high": 120.34,
            "low": 119.89,
            "close": 120.08
        },
        "1616182200": {
            "date": "19-03-2021",
            "open": 120.09,
            "high": 120.97,
            "low": 119.85,
            "close": 119.87
        }
    },
    "error": null
}
